[
{"p":"ChIJXZtUf6g_b0cRZ9STp0tZ1l0","x":"46.6501488","y":"16.1877095","n":"Lagev bar","t":"2","c":"32","s":"4.2","d":"0","a":"29,11,18,104","l":"Ulica dr. Vrbnjaka 10a, 9000 Murska Sobota, Slovenia","b":"2","w":"0,2,4"},
{"p":"ChIJYwZBXf64ekcR6UWLaQdmG5k","x":"46.2654607","y":"14.3234357","n":"Ag Gantar","t":"4","c":"51","s":"4.6","d":"0","a":"250,69,261,262","l":"Kranjska cesta 22, 4202 Naklo, Slovenia","b":"2","w":"0,2,4"},
{"p":"ChIJgYPmPiQzZUcRNeCHDv3VAH8","x":"46.05632119999999","y":"14.5044406","n":"Galerija Kofi Design","t":"2","c":"8","s":"4.6","d":"0","a":"29,250,11,104","l":"Kersnikova ulica 10, 1000 Ljubljana, Slovenia","b":"2","w":"0,2,4"},
{"p":"ChIJc4gAt2gyZUcREpk-FUz0fwQ","x":"46.0637933","y":"14.5446183","n":"Škrnic'lj restavracija - Andrej Belovič s.p.","t":"0","c":"112","s":"4.6","d":"0","a":"124,51,55,109","l":"Šmartinska c. 152, 1000 Ljubljana, Slovenia","b":"2","w":"0,2,4"},
{"p":"ChIJgfftgWQtZUcRghGloQ1WwlE","x":"46.0487725","y":"14.5060959","n":"Quicksilver Store","t":"4","c":"27","s":"3.9","d":"0","a":"250,314,181,52","l":"Mestni trg 16, 1000 Ljubljana, Slovenia","b":"2","w":"0,2,4"},
]
