[
{"p":"ChIJ9bJXvX9fKowRllV_emkPzQ0","x":"10.4977818","y":"-66.9195945","n":"DAIO TECHNOLOGY CA","t":"999","c":"0","s":"0.0","d":"0","a":"250,181,179,178","l":"Av baralt, Centro Comercial Doral Baralt, local PB 60, Caracas 1010, Distrito Capital, Venezuela","b":"4","w":"0"},
{"p":"ChIJ9bJXvX9fKowRllV_emkPzQ0","x":"10.4977818","y":"-66.9195945","n":"DAIO TECHNOLOGY CA","t":"4","c":"0","s":"0.0","d":"0","a":"250,181,179,178","l":"Av baralt, Centro Comercial Doral Baralt, local PB 60, Caracas 1010, Distrito Capital, Venezuela","b":"4","w":"0"},
{"p":"ChIJ5QuWrwZfKowRH1ISf8MSRRM","x":"10.4977733","y":"-66.91963849999999","n":"Inversiones Lozano3112 ca","t":"4","c":"0","s":"0.0","d":"0","a":"250,181,104,104","l":"Av Baralt entre las esquina buscaré a Carmen Cc doral baralt nivel mezzanina local 135 y 136, Caracas 1020, Distrito Capital, Venezuela","b":"4","w":"0"},
{"p":"ChIJTR1iJJhfKowRDyHLaOqvaZ0","x":"10.5049913","y":"-66.91787699999999","n":"Inversiones 1G12, C.A","t":"4","c":"0","s":"0.0","d":"0","a":"250,181,104,104","l":"Av Baralt con Av. Universidad CC Metrocenter Nivel Colonial Local MP-01 Urb, Caracas 1012, Caracas 1012, Distrito Capital, Venezuela","b":"4","w":"0"},
{"p":"ChIJK-Pr-cJfKowRxMBcj_enlz0","x":"10.5045316","y":"-66.9169263","n":"Accesorios Aquamoda, C.A","t":"4","c":"0","s":"0.0","d":"0","a":"250,181,178,179","l":"Av. Baralt con Av. Universidad CC Metrocenter Nivel Colonial Local Stand 8 y 9 Urb, Caracas 1012, Caracas 1012, Distrito Capital, Venezuela","b":"4","w":"0"},
{"p":"ChIJO9zmhn5fKowR6x7GTypMFtc","x":"10.5020271","y":"-66.9092472","n":"JJ Sport C.A","t":"4","c":"0","s":"0.0","d":"0","a":"250,181,104,104","l":"Mercado bolivariano la Hoyada, Pasillo Ecuador, Local 2010, Caracas 1011, Caracas 1011, Distrito Capital, Venezuela","b":"4","w":"0"},
{"p":"ChIJr-p04yhfKowRXENyclTEhKs","x":"10.5057376","y":"-66.9106943","n":"Inversiones elham c.a","t":"4","c":"0","s":"0.0","d":"0","a":"250,181,104,104","l":"Esq el cuji edificio torre el cuji piso pb local b Urb parroquia, Caracas 1020, Distrito Capital, Venezuela","b":"4","w":"0"},
{"p":"ChIJIf5PsDRfKowRunec7GvFpyE","x":"10.5027181","y":"-66.9184133","n":"Unidad de Didtr. De alimentos MME98, C.A","t":"4","c":"0","s":"0.0","d":"0","a":"288,181,21,104","l":"Calle Av Baralt Edif. Bloque 2 Piso PB Local 1-D Urba, Av. Baralt, Caracas 1020, Distrito Capital, Venezuela","b":"4","w":"0"},
{"p":"ChIJIf5PsDRfKowRunec7GvFpyE","x":"10.5027181","y":"-66.9184133","n":"Unidad de Didtr. De alimentos MME98, C.A","t":"4","c":"0","s":"0.0","d":"0","a":"288,181,21,104","l":"Calle Av Baralt Edif. Bloque 2 Piso PB Local 1-D Urba, Av. Baralt, Caracas 1020, Distrito Capital, Venezuela","b":"4","w":"0"},
{"p":"ChIJ__PT2PheKowRzzhK-ijkz1U","x":"10.5064943","y":"-66.9483068","n":"Reparaciones y Repuestos Cesar C.A","t":"4","c":"3","s":"5","d":"0","a":"250,178,181,173","l":"Av. El Atlántico, Edificio Centro Industrial Don Salomon, PB Local 17H, Caracas 1030, Distrito Capital, Venezuela","b":"4","w":"0"},
{"p":"ChIJc4PBXyJfKowR4lTRmQdc9R8","x":"10.5077898","y":"-66.9470887","n":"Inversiones Stargold, C.A.","t":"4","c":"10","s":"4.8","d":"0","a":"288,21,55,18","l":"G353+457, Caracas 1030, Capital District, Venezuela","b":"4","w":"0"},
{"p":"ChIJXyKmWNlfKowRqZuWYxkxr5c","x":"10.5064312","y":"-66.9088536","n":"El chacal café","t":"2","c":"0","s":"0.0","d":"0","a":"29,55,7,109","l":"local 9, edificio Fondo común, PB Avenida Fuerzas Armadas, Caracas 1011, Distrito Capital, Venezuela","b":"4","w":"0"},
{"p":"ChIJjzcukqtfKowRZRX1wiEtD_k","x":"10.4914716","y":"-66.9398066","n":"Inversiones Seblo","t":"4","c":"0","s":"0.0","d":"0","a":"250,181,104,104","l":"Avenida principal de San Martin, centro comercial San Martin, zona 71, local 103-104, Caracas 1020, Distrito Capital, Venezuela","b":"4","w":"0"},
{"p":"ChIJ5WRo32htZo4Raj0ZmcjSM1s","x":"7.7567002","y":"-72.2341011","n":"Auto repuestos 2000","t":"4","c":"1","s":"5","d":"0","a":"69,181,262,250","l":"QQ48+M9J, Calle 5 Bis, San Cristóbal 5001, Táchira, Venezuela","b":"4","w":"0"},
{"p":"ChIJAZvfqmRfKowR5DI_jyGpzf4","x":"10.4737156","y":"-66.94523869999999","n":"Ponkes mil sabores","t":"2","c":"0","s":"0.0","d":"0","a":"117,11,55,142","l":"Zona 01, Centro Comercial San Martín, local 35 , Caracas 1020, Caracas 1020, Caracas 1020, Distrito Capital, Venezuela","b":"4","w":"0"},
{"p":"ChIJiawblF5fKowR3fFheEEVAxo","x":"10.5021","y":"-66.9062856","n":"Global PC Venezuela","t":"4","c":"4","s":"3.5","d":"0","a":"250,181,104,104","l":"Avenida principal, centro parque Carabobo, planta baja, local N1-127, Avenida Universidad, Caracas 1011, Distrito Capital, Venezuela","b":"4","w":"0"},
{"p":"ChIJZ-b0tYhZKowRJmMGqXpCDik","x":"10.4914119","y":"-66.85828649999999","n":"Michael's Taires","t":"4","c":"0","s":"0.0","d":"0","a":"250,181,104,104","l":"Avenida Libertador con calle muñeco, edificio centro Mancom, piso PB, F4RR+HM8, Caracas 1060, Miranda, Venezuela","b":"4","w":"0"},
{"p":"ChIJcTXHsWNZKowRPvWvAiwwd7w","x":"10.4906402","y":"-66.8738671","n":"Ak Aromas y Sabores","t":"0","c":"11","s":"4.5","d":"0","a":"140,7,150,124","l":"Bello Monte, Caracas 1050, Distrito Capital, Venezuela","b":"4","w":"0"},
{"p":"ChIJL08VpapZKowRTd43rxu4aUA","x":"10.4948706","y":"-66.8803839","n":"Centro de Estética Shadday 1006 CA","t":"4","c":"3","s":"5","d":"0","a":"250,91,254,93","l":"F4V9+WRX, Caracas 1050, Capital District, Venezuela","b":"4","w":"0"},
{"p":"ChIJOz-BD7FZKowRtmtd7J4oMlY","x":"10.4944201","y":"-66.8777815","n":"V58 Store City Market 6","t":"4","c":"0","s":"0.0","d":"0","a":"181,21,93,179","l":"F4VC+QV8, Caracas 1050, Capital District, Venezuela","b":"4","w":"0"},
{"p":"ChIJn6rdhatZKowRNZC1etUja8M","x":"10.4943925","y":"-66.8777805","n":"V58 Store City Market 5","t":"4","c":"0","s":"0.0","d":"0","a":"250,181,179,262","l":"Piso 3, C.C City Market, Nivel Bazar, Local B408, Blvr. de Sabana Grande, Caracas 1050, Distrito Capital, Venezuela","b":"4","w":"0"},
{"p":"ChIJi347-jpZKowR6oeIzmRJI1s","x":"10.4944241","y":"-66.87779119999999","n":"V58 Store City Market 4","t":"4","c":"0","s":"0.0","d":"0","a":"250,181,179,262","l":"C.C City Market, Nivel PB, Local Arca, N° 456 Blvr. de Sabana Grande, Caracas 1050, Distrito Capital, Venezuela","b":"4","w":"0"},
{"p":"ChIJnQFogmpZKowREQaEHD21YqM","x":"10.4944353","y":"-66.8777778","n":"V58 Store City Market 3","t":"4","c":"0","s":"0.0","d":"0","a":"250,181,179,262","l":"F4VC+QVH, Caracas 1050, Capital District, Venezuela","b":"4","w":"0"},
{"p":"ChIJHVdGfG5ZKowRwDZ4noRJb1c","x":"10.4944031","y":"-66.8777805","n":"V58 Store City Market 2","t":"4","c":"0","s":"0.0","d":"0","a":"250,181,179,262","l":"Piso 2, C.C City Market, Nivel Bazar, Local B330, Blvr. de Sabana Grande, Caracas 1050, Distrito Capital, Venezuela","b":"4","w":"0"},
{"p":"ChIJu4hCWiRfKowR8yVgJzvPkds","x":"10.5116471","y":"-66.9471867","n":"Tienda El Molino, C.A.","t":"4","c":"3","s":"4.3","d":"0","a":"288,21,46,142","l":"Av. Bulevar España, Entre 2da y 3ra Avenida, PB Local 51, Caracas 1030, Distrito Capital, Venezuela","b":"4","w":"0"},
{"p":"ChIJtbHfbvdeKowRIMBr4zec4Lo","x":"10.5116096","y":"-66.9471376","n":"Lunch Starbucks Café, C.A.","t":"0","c":"519","s":"4","d":"0","a":"29,142,124,55","l":"Local 50 Blvr. Av. España, Caracas 1030, Distrito Capital, Venezuela","b":"4","w":"0"},
{"p":"ChIJ8cLBAtBdKowRjzGFowLmj04","x":"10.5964491","y":"-66.9498682","n":"Inversiones Sunnet, C.A.","t":"4","c":"0","s":"0.0","d":"0","a":"288,21,142,55","l":"Calle Padre Machado, Local 45-07, Frente a la Plaza de los Maestros, Maiquetía 1161, Maiquetía 1161, La Guaira, Venezuela","b":"4","w":"0"},
]
