[
{"p":"ChIJ-138P5z7ykARMiwbbq9UHUE","x":"47.15507729999999","y":"27.58851379999999","n":"IL PASSO","t":"4","c":"13","s":"3.8","d":"0","a":"250,182,52,20","l":"Strada Palas 7A, Iași 700051, Romania","b":"2","w":"0,2,4"},
{"p":"ChIJv05tXeBHRkcRxKF2fDI0yjs","x":"47.0620315","y":"21.9329948","n":"Rotexim Atic","t":"4","c":"65","s":"4.1","d":"0","a":"250,244,81,14","l":"Strada Dunărea 27, Oradea, Romania","b":"2","w":"0,2,4"},
{"p":"ChIJq6SxTQjwukARCf6mpxcACCE","x":"44.2039378","y":"28.6323175","n":"IL PASSO","t":"4","c":"15","s":"4.2","d":"0","a":"250,182,52,20","l":"Bulevardul Alexandru Lăpușneanu 116C, Constanța 900419, Romania","b":"2","w":"0,2,4"},
{"p":"ChIJi6Zua0e-TEcRLucx0M0_NsU","x":"45.6903412","y":"24.7948414","n":"Sâmbăta de Sus Monastery","t":"999","c":"7983","s":"4.8","d":"0","a":"276,299,230,104","l":"DC79, Stațiunea Climaterică Sâmbăta 507267, Romania","b":"2","w":"0,2,4"},
{"p":"ChIJHdp3I64DskARxI00mZQbPDU","x":"44.42937999999999","y":"26.11016","n":"Antrepriza Construcţii Montaj 4 S.A.","t":"4","c":"0","s":"0.0","d":"0","a":"250,181,104,104","l":"Str. Barasch Iuliu, 4A, Bucuresti-Sector 3, Bucuresti, 30791, București 030167, Romania","b":"2","w":"0,2,4"},
{"p":"ChIJB8QKfftJRkcRk6I1JGSawVA","x":"47.06986199999999","y":"21.9223709","n":"biciclaria.ro","t":"4","c":"19","s":"4.7","d":"0","a":"65,250,261,262","l":"Bulevardul Dacia 48, Oradea 410346, Romania","b":"2","w":"0,2,4"},
]
