[
{"p":"ChIJBzTNEtINfI4RZCRaIwbWawk","x":"8.697346999999999","y":"-69.2070457","n":"Mundo Repuestos Panda","t":"999","c":"0","s":"0.0","d":"0","a":"181,262,68,250","l":"MQWV+W5P, Guanarito 3354, Portuguesa, Venezuela","b":"4","w":"0"},
{"p":"ChIJ-TZMk8f1fI4RJckrxuysb6E","x":"9.045670399999999","y":"-69.7453301","n":"Kau Kids","t":"4","c":"0","s":"0.0","d":"0","a":"52,181,54,224","l":"AV. UNDA ENTRE CARRERAS 6 Y 7, Centro Comercial LOS ANDENES, 3350, Av. Unda, Guanare 3350, Portuguesa, Venezuela","b":"4","w":"0"},
{"p":"ChIJAwiGE8VZKowRz5-c7dabJaY","x":"10.4537917","y":"-66.82034689999999","n":"Bubbles fresh","t":"999","c":"0","s":"0.0","d":"0","a":"187,181,191,104","l":"la guairita, local 67 Avenida Luis De Camoens, Caracas 1073, Miranda, Venezuela","b":"4","w":"0"},
{"p":"ChIJfcVo9lltZo4RZyZrAPUcIqA","x":"7.757736499999999","y":"-72.2317076","n":"AUTO REPUESTOS CHERYFORD","t":"999","c":"7","s":"3.4","d":"0","a":"250,69,262,181","l":"carrera 9 calle 4 y, C. 4 Bis, San Cristóbal 5001, Táchira, Venezuela","b":"4","w":"0"},
]
